LICENSE
README.md
setup.py
stage_reporter/__init__.py
stage_reporter/module1.py
stage_reporter.egg-info/PKG-INFO
stage_reporter.egg-info/SOURCES.txt
stage_reporter.egg-info/dependency_links.txt
stage_reporter.egg-info/requires.txt
stage_reporter.egg-info/top_level.txt
stage_reporter.egg-info/.ipynb_checkpoints/SOURCES-checkpoint.txt