Metadata-Version: 2.1
Name: stage-reporter
Version: 0.2.0
Summary: Testing installation of Package
Home-page: https://github.com/DonnieData/stage-reporter
Author: Donnell Jackson
Author-email: donnie.developer@gmail.com
License: MIT
Download-URL: https://github.com/DonnieData/stage-reporter/archive/refs/tags/v.0.2.0.tar.gz
Project-URL: Bug Tracker, https://github.com/DonnieData/stage-reporter/issues
Keywords: pypi,stage_reporter,script report,tracking
Platform: UNKNOWN
Classifier: Development Status :: 3 - Alpha
Classifier: Intended Audience :: Developers
Classifier: Topic :: Software Development :: Documentation
Classifier: License :: OSI Approved :: MIT License
Classifier: Programming Language :: Python :: 3
Classifier: Programming Language :: Python :: 3.7
Classifier: Programming Language :: Python :: 3.8
Classifier: Programming Language :: Python :: 3.9
License-File: LICENSE
